Metadata-Version: 1.0
Name: mytestlib-abc
Version: 1.0.0
Summary: My Test Library.
Home-page: https://pypi.org/project/setuptools/
Author: タパ　ブディバル
Author-email: b-thapa@kbsanhe.co.jp
License: UNKNOWN
Platform: UNKNOWN
